pynng/_aio.py
pynng/_version.py
pynng/tls.py
pynng/nng.py
pynng/exceptions.py
pynng/_nng.abi3.so
pynng/options.py
pynng/__init__.py
pynng/sockaddr.py
pynng_tls-0.4.1.dist-info/top_level.txt
pynng_tls-0.4.1.dist-info/RECORD
pynng_tls-0.4.1.dist-info/METADATA
pynng_tls-0.4.1.dist-info/WHEEL
test/_test_util.py
test/test_msg.py
test/test_tls.py
test/test_protocols.py
test/test_api.py
test/test_aio.py
test/test_options.py
test/test_pipe.py
test/__init__.py
