Metadata-Version: 2.1
Name: pynng-tls
Version: 0.4.1
Summary: Networking made simply using nng
Home-page: https://github.com/codypiersall/pynng
Author: Cody Piersall
Author-email: cody.piersall@gmail.com
License: MIT
Keywords: networking nng nanomsg zmq messaging message trio asyncio
Platform: UNKNOWN
Classifier: Development Status :: 3 - Alpha
Classifier: Framework :: AsyncIO
Classifier: Framework :: Trio
Classifier: License :: OSI Approved :: MIT License
Classifier: Operating System :: OS Independent
Classifier: Programming Language :: Python :: 3 :: Only
Classifier: Programming Language :: Python :: 3.5
Classifier: Programming Language :: Python :: 3.6
Classifier: Programming Language :: Python :: 3.7
Classifier: Programming Language :: Python :: 3.8
Classifier: Topic :: Software Development :: Libraries
Classifier: Topic :: System :: Networking
